absresgetter/__init__.py
absresgetter/main.py
absresgetter-0.0.12.dist-info/LICENSE
absresgetter-0.0.12.dist-info/METADATA
absresgetter-0.0.12.dist-info/WHEEL
absresgetter-0.0.12.dist-info/top_level.txt
absresgetter-0.0.12.dist-info/RECORD
