Metadata-Version: 2.1
Name: absresgetter
Version: 0.0.12
Summary: Get absolute resource path of exterior package
Home-page: https://github.com/yjg30737/absresgetter.git
Author: Jung Gyu Yoon
Author-email: yjg30737@gmail.com
License: MIT
Platform: UNKNOWN
License-File: LICENSE
